cheb3/__init__.py
cheb3/account.py
cheb3/connection.py
cheb3/constants.py
cheb3/contract.py
cheb3/helper.py
cheb3/utils.py
cheb3-1.0.1.dist-info/licenses/LICENSE
cheb3-1.0.1.dist-info/METADATA
cheb3-1.0.1.dist-info/WHEEL
cheb3-1.0.1.dist-info/top_level.txt
cheb3-1.0.1.dist-info/RECORD
